Workbook
Name Slicer_Category: #N/A
Name Slicer_Months__Order_Date: #N/A
Name Slicer_Product: #N/A

Sheet online shopping data
A1: Order ID | B1: Customer ID | C1: Product | D1: Category | E1: Price | F1: Quantity | G1: Total Amount | H1: Order Date | I1: Payment Method | J1: City | K1: Delivery Status | L1: Rating | M1: Discount | N1: Profit | O1: Return Status
A2: 1 | B2: 8575 | C2: Bag | D2: Accessories | E2: 40335 | F2: 4 | G2: 161340 | H2: 45446 | I2: Card | J2: Chennai | K2: Pending | L2: 3 | M2: 0.21698388 | N2: 13393.82 | O2: Not Returned
A3: 2 | B3: 4227 | C3: Headphones | D3: Electronics | E3: 13653 | F3: 4 | G3: 54612 | H3: 45372 | I3: Card | J3: Mumbai | K3: Pending | L3: 3.5 | M3: 0.2664202 | N3: 1833.86 | O3: Returned
A4: 3 | B4: 9934 | C4: Phone | D4: Electronics | E4: 38082 | F4: 1 | G4: 38082 | H4: 45378 | I4: Card | J4: Mumbai | K4: Delivered | L4: 4.2 | M4: 0.19585316 | N4: 3966.12 | O4: Not Returned
A5: 4 | B5: 8854 | C5: Phone | D5: Electronics | E5: 22294 | F5: 1 | G5: 22294 | H5: 45524 | I5: NetBanking | J5: Delhi | K5: Cancelled | L5: 1.8 | M5: 0.064998206 | N5: 5239.13 | O5: Not Returned
A6: 5 | B6: 5330 | C6: Shoes | D6: Fashion | E6: 8165 | F6: 4 | G6: 32660 | H6: 45593 | I6: UPI | J6: Bangalore | K6: Delivered | L6: 2.2 | M6: 0.088939682 | N6: 6893.23 | O6: Returned
A7: 6 | B7: 6195 | C7: Watch | D7: Accessories | E7: 37080 | F7: 5 | G7: 185400 | H7: 45338 | I7: NetBanking | J7: Mumbai | K7: Delivered | L7: 4.1 | M7: 0.27913096 | N7: 3869.12 | O7: Not Returned
A8: 7 | B8: 3024 | C8: Shoes | D8: Fashion | E8: 27641 | F8: 2 | G8: 55282 | H8: 45457 | I8: Cash | J8: Delhi | K8: Delivered | L8: 2.5 | M8: 0.26843982 | N8: 1744.71 | O8: Returned
A9: 8 | B9: 9080 | C9: Shoes | D9: Fashion | E9: 35323 | F9: 5 | G9: 176615 | H9: 45484 | I9: Cash | J9: Mumbai | K9: Pending | L9: 4.9 | M9: 0.21785103 | N9: 14508.74 | O9: Returned
A10: 9 | B10: 3049 | C10: Laptop | D10: Electronics | E10: 48951 | F10: 4 | G10: 195804 | H10: 45358 | I10: Cash | J10: Chennai | K10: Cancelled | L10: 2.9 | M10: 0.17041567 | N10: 25373.13 | O10: Returned
A11: 10 | B11: 2953 | C11: Watch | D11: Accessories | E11: 3128 | F11: 4 | G11: 12512 | H11: 45439 | I11: Cash | J11: Delhi | K11: Cancelled | L11: 1.8 | M11: 0.13069453 | N11: 2118.35 | O11: Not Returned
A12: 11 | B12: 6860 | C12: Watch | D12: Accessories | E12: 26619 | F12: 3 | G12: 79857 | H12: 45507 | I12: NetBanking | J12: Bangalore | K12: Pending | L12: 4.5 | M12: 0.052375747 | N12: 19774.53 | O12: Not Returned
A13: 12 | B13: 4368 | C13: Phone | D13: Electronics | E13: 35187 | F13: 1 | G13: 35187 | H13: 45548 | I13: Card | J13: Chennai | K13: Delivered | L13: 1.4 | M13: 0.21977207 | N13: 2822.98 | O13: Not Returned
... A1001: 1000 | B1001: 8816 | C1001: Shoes | D1001: Electronics | E1001: 25079 | F1001: 4 | G1001: 100316 | H1001: 45297 | I1001: Cash | J1001: Delhi | K1001: Pending | L1001: 3.7 | M1001: 0.11894075 | N1001: 18163.14 | O1001: Returned

Sheet Questions
B2: QUESTIONS
B5: 1. Calculate the total sales using the SUM function. | L5: 9. Use HLOOKUP function to find discount percentage based on product category.
B7: 2. Find the average sales using the AVERAGE function. | L7: 10. Use IF function to classify orders as “High Sale” or “Low Sale”.
B9: 3. Count the total number of orders using the COUNT function. | L9: 11. Find the highest and lowest sales using the MAX and MIN functions.
B11: 4. Count how many orders are returned using the COUNTIF function. | L11: 12. Calculate profit using a formula combining TotalAmount, Discount, and Cost.
B13: 5. Calculate total sales for a specific category (e.g., Electronics) using the SUMIF function. | L13: 13. Use COUNTIF function to count how many orders are from a specific payment method (e.g., Cash on Delivery).
B15: 6. Calculate total sales for a specific city using the SUMIF function. | L15: 14. Use SUMIFS function to calculate total sales for a specific category and city.
B17: 7. Use VLOOKUP function to find the category of a product from a separate table. | L17: 15. Use VLOOKUP with IF to display “Valid” or “Invalid” product based on lookup result.
B19: 8. Use VLOOKUP function to find the unit price of a product.

Sheet Answers
B2: ANSWERS
B5: Question 1 | E5: Question 2 | H5: Question 3 | K5: Question 4 | N5: Question 5 | Q5: Question 6
B6: Total Sales | C6: =SUM('online shopping data'!G2:G1001) -> 78181408 | E6: Average Sales | F6: =AVERAGE('online shopping data'!G2:G1001) -> 78181.408 | H6: Total No. of Orders | I6: =COUNT('online shopping data'!A2:A1001) -> 1000 | K6: Returned Orders | L6: =COUNTIF('online shopping data'!O2:O1001,"Returned") -> 486 | N6: Category | O6: Total Amount | Q6: City | R6: Total Amount
N7: Electronics | O7: =SUMIF('online shopping data'!D2:D1001,Answers!N7,'online shopping data'!G2:G1001) -> 28103279 | Q7: Kolkata | R7: =SUMIF('online shopping data'!J2:J1001,Answers!Q7,'online shopping data'!G2:G1001) -> 16568982
B8: VLOOKUP Function
I9: HLOOKUP Function
B10: Product | C10: Category | D10: Price | F10: Question 7
B11: Bag | C11: Accessories | D11: 40335 | F11: Product | G11: Category | I11: Category | J11: Accessories | K11: Electronics | L11: Electronics | M11: Electronics | N11: Fashion | O11: Accessories | P11: Fashion | Q11: Fashion
B12: Headphones | C12: Electronics | D12: 13653 | F12: Headphones | G12: =VLOOKUP(F12,B10:D24,2,0) -> Electronics | I12: Discount | J12: 0.21698388 | K12: 0.2664202 | L12: 0.19585316 | M12: 0.064998206 | N12: 0.088939682 | O12: 0.27913096 | P12: 0.26843982 | Q12: 0.21785103
B13: Phone | C13: Electronics | D13: 38082
B14: Phone | C14: Electronics | D14: 22294 | K14: Question 9
B15: Shoes | C15: Fashion | D15: 8165 | F15: Question 8 | K15: Category | L15: Discount
B16: Watch | C16: Accessories | D16: 37080 | F16: product | G16: Price | K16: Accessories | L16: =HLOOKUP(K16,I11:Q12,2,0) -> 0.21698388
B17: Shoes | C17: Fashion | D17: 27641 | F17: Laptop | G17: =VLOOKUP(F17,B10:D24,3,0) -> 48951
B18: Shoes | C18: Fashion | D18: 35323
B19: Laptop | C19: Electronics | D19: 48951
B20: Watch | C20: Accessories | D20: 3128 | F20: Question 15 | I20: Question 10 | L20: Question 11 | Q20: Question 12
B21: Watch | C21: Accessories | D21: 26619 | F21: Product | G21: Result | I21: Example Condition : >50000= High | L21: Highest and Lowest Sales | Q21: Profit Calculation Formula
B22: Phone | C22: Electronics | D22: 35187 | F22: Phone | G22: =IF(ISNA(VLOOKUP(F22,B11:C25,1,0)),"Invalid","Valid") -> Valid | I22: Total Amount | J22: High/Low Sales | L22: MAX | M22: =MAX('online shopping data'!G2:G1001) -> 249460 | N22: MIN | O22: =MIN('online shopping data'!G2:G1001) -> 603 | Q22: If Cost = 70% of Price
B23: Headphones | C23: Electronics | D23: 45423 | I23: 161340 | J23: =IF(I23>50000,"High Sale","Low Sale") -> High Sale | Q23: PROFIT | R23: =('online shopping data'!G2-'online shopping data'!M2)-('online shopping data'!E2*0.7*'online shopping data'!F2) -> 48401.783
B24: Laptop | C24: Electronics | D24: 36008 | I24: 54612 | J24: =IF(I24>50000,"High Sale","Low Sale") -> High Sale
I25: 38082 | J25: =IF(I25>50000,"High Sale","Low Sale") -> Low Sale | L25: Question 13 | P25: Question 14
I26: 22294 | J26: =IF(I26>50000,"High Sale","Low Sale") -> Low Sale | L26: Payement Method | N26: Count Order | P26: Category | Q26: City | R26: Total sales
I27: 32660 | J27: =IF(I27>50000,"High Sale","Low Sale") -> Low Sale | L27: Cash | N27: =COUNTIF('online shopping data'!I2:I1001,Answers!L27) -> 241 | P27: Accessories | Q27: Mumbai | R27: =SUMIFS('online shopping data'!G2:G1001,'online shopping data'!D2:D1001,Answers!P27,'online shopping data'!J2:J1001,Answers!Q27) -> 5316972
I28: 185400 | J28: =IF(I28>50000,"High Sale","Low Sale") -> High Sale
I29: 55282 | J29: =IF(I29>50000,"High Sale","Low Sale") -> High Sale
I30: 176615 | J30: =IF(I30>50000,"High Sale","Low Sale") -> High Sale
I31: 195804 | J31: =IF(I31>50000,"High Sale","Low Sale") -> High Sale
I32: 12512 | J32: =IF(I32>50000,"High Sale","Low Sale") -> Low Sale
I33: 79857 | J33: =IF(I33>50000,"High Sale","Low Sale") -> High Sale
I34: 35187 | J34: =IF(I34>50000,"High Sale","Low Sale") -> Low Sale
I35: 136269 | J35: =IF(I35>50000,"High Sale","Low Sale") -> High Sale

Sheet Pivot Table
A1: PIVOT TABLE ANALYSIS
B3: Total Sales by Category | F3: Sales by City | J3: Profit by Category | N3: Top Selling Products
B4: Row Labels | C4: Sum of Total Amount | F4: Row Labels | G4: Sum of Total Amount | J4: Row Labels | K4: Sum of Profit | N4: Row Labels | O4: Sum of Quantity
B5: Accessories | C5: 27473470 | F5: Bangalore | G5: 15090761 | J5: Accessories | K5: 3462138.8 | N5: Bag | O5: 494
B6: Electronics | C6: 28103279 | F6: Chennai | G6: 15264710 | J6: Electronics | K6: 3605909.6 | N6: Headphones | O6: 479
B7: Fashion | C7: 22604659 | F7: Delhi | G7: 16935883 | J7: Fashion | K7: 2997737.5 | N7: Laptop | O7: 511
B8: Grand Total | C8: 78181408 | F8: Kolkata | G8: 16568982 | J8: Grand Total | K8: 10065786 | N8: Phone | O8: 431
F9: Mumbai | G9: 14321072 | N9: Shoes | O9: 500
F10: Grand Total | G10: 78181408 | N10: Watch | O10: 521
N11: Grand Total | O11: 2936
B12: Payment Method Analysis | F12: Return Analysis
B13: Row Labels | C13: Sum of Total Amount | F13: Row Labels | G13: Count of Return Status | J13: Discount Average | N13: Monthly Sales Trend
B14: Card | C14: 19421997 | F14: Not Returned | G14: 514 | J14: Row Labels | K14: Average of Discount | N14: Row Labels | O14: Sum of Total Amount
B15: Cash | C15: 20971122 | F15: Returned | G15: 486 | J15: Accessories | K15: 0.17594345 | N15: Jan | O15: 5941187
B16: NetBanking | C16: 17709762 | F16: Grand Total | G16: 1000 | J16: Electronics | K16: 0.17308429 | N16: Feb | O16: 6434381
B17: UPI | C17: 20078527 | J17: Fashion | K17: 0.17153365 | N17: Mar | O17: 7257561
B18: Grand Total | C18: 78181408 | J18: Grand Total | K18: 0.17362601 | N18: Apr | O18: 5845654
N19: May | O19: 6832407
N20: Jun | O20: 6442679
B21: Profit vs. Sales Comparision | F21: Category vs. City | N21: Jul | O21: 7559886
B22: Row Labels | C22: Sum of Total Amount | D22: Sum of Profit | F22: Sum of Total Amount | G22: Column Labels | N22: Aug | O22: 6259636
B23: Accessories | C23: 27473470 | D23: 3462138.8 | F23: Row Labels | G23: Bangalore | H23: Chennai | I23: Delhi | J23: Kolkata | K23: Mumbai | L23: Grand Total | N23: Sep | O23: 5662652
B24: Electronics | C24: 28103279 | D24: 3605909.6 | F24: Accessories | G24: 5130999 | H24: 5364245 | I24: 5327457 | J24: 6333797 | K24: 5316972 | L24: 27473470 | N24: Oct | O24: 6580893
B25: Fashion | C25: 22604659 | D25: 2997737.5 | F25: Electronics | G25: 5062701 | H25: 5826523 | I25: 6470009 | J25: 5922636 | K25: 4821410 | L25: 28103279 | N25: Nov | O25: 6559214
B26: Grand Total | C26: 78181408 | D26: 10065786 | F26: Fashion | G26: 4897061 | H26: 4073942 | I26: 5138417 | J26: 4312549 | K26: 4182690 | L26: 22604659 | N26: Dec | O26: 6805258
F27: Grand Total | G27: 15090761 | H27: 15264710 | I27: 16935883 | J27: 16568982 | K27: 14321072 | L27: 78181408 | N27: Grand Total | O27: 78181408

Sheet Pivot Chart
A1: PIVOT CHART ANALYSIS
